myTesla.py
myTesla2.py
myTesla/__init__.py
myTesla/myTesla.py
myTesla-1.1.dist-info/LICENSE
myTesla-1.1.dist-info/METADATA
myTesla-1.1.dist-info/WHEEL
myTesla-1.1.dist-info/top_level.txt
myTesla-1.1.dist-info/RECORD
