Metadata-Version: 2.1
Name: myTesla
Version: 1.1
Summary: Python client to interact with your tesla.
Home-page: https://github.com/zmsp/python-my-tesla
Author: Zobair Shahadat
Author-email: cheezyspam21@gmail.com
License: Apache License 2.0
Platform: UNKNOWN
Classifier: Operating System :: OS Independent
